{"namedChunkGroups":{"polyfill":{"name":"polyfill","assets":[{"name":"webpack-runtime-f513447bffaa63b50010.js","size":5696},{"name":"polyfill-5abccd0ea9f5cedded36.js","size":85294}],"filteredAssets":0,"assetsSize":90990,"filteredAuxiliaryAssets":2,"auxiliaryAssetsSize":228883},"app":{"name":"app","assets":[{"name":"webpack-runtime-f513447bffaa63b50010.js","size":5696},{"name":"styles.74c3acc855b59ef6f956.css","size":148360},{"name":"framework-c7a97ca6659000a10433.js","size":129927},{"name":"app-e723c4ebbc0c587518bd.js","size":102745}],"filteredAssets":0,"assetsSize":386728,"filteredAuxiliaryAssets":3,"auxiliaryAssetsSize":702363},"component---src-pages-404-js":{"name":"component---src-pages-404-js","assets":[{"name":"styles.74c3acc855b59ef6f956.css","size":148360},{"name":"cb1608f2-0992558c61e10c50e999.js","size":1707},{"name":"a9a7754c-816c2ce5780ea77fc95e.js","size":2187},{"name":"commons-e529fd12877672bf1c00.js","size":88589},{"name":"component---src-pages-404-js-058df25e754af4518db9.js","size":769}],"filteredAssets":0,"assetsSize":241612,"filteredAuxiliaryAssets":5,"auxiliaryAssetsSize":1628985},"component---src-pages-about-js":{"name":"component---src-pages-about-js","assets":[{"name":"styles.74c3acc855b59ef6f956.css","size":148360},{"name":"cb1608f2-0992558c61e10c50e999.js","size":1707},{"name":"a9a7754c-816c2ce5780ea77fc95e.js","size":2187},{"name":"commons-e529fd12877672bf1c00.js","size":88589},{"name":"6cf1ab06f31558239a7851f0ba16511ad5d09edf-fe5878115318c1cf7033.js","size":15944},{"name":"component---src-pages-about-js-a75361efb4041cdeb4e8.js","size":5810}],"filteredAssets":0,"assetsSize":262597,"filteredAuxiliaryAssets":11,"auxiliaryAssetsSize":6099672},"component---src-pages-blogs-js":{"name":"component---src-pages-blogs-js","assets":[{"name":"styles.74c3acc855b59ef6f956.css","size":148360},{"name":"cb1608f2-0992558c61e10c50e999.js","size":1707},{"name":"a9a7754c-816c2ce5780ea77fc95e.js","size":2187},{"name":"commons-e529fd12877672bf1c00.js","size":88589},{"name":"6cf1ab06f31558239a7851f0ba16511ad5d09edf-fe5878115318c1cf7033.js","size":15944},{"name":"1f7a1e317deb6f679edf2553d304721106db1456-6c99e90d963f3174ecba.js","size":11533},{"name":"component---src-pages-blogs-js-1d3d449acdeba14cc623.js","size":3303}],"filteredAssets":0,"assetsSize":271623,"filteredAuxiliaryAssets":7,"auxiliaryAssetsSize":1754191},"component---src-pages-experience-js":{"name":"component---src-pages-experience-js","assets":[{"name":"styles.74c3acc855b59ef6f956.css","size":148360},{"name":"cb1608f2-0992558c61e10c50e999.js","size":1707},{"name":"a9a7754c-816c2ce5780ea77fc95e.js","size":2187},{"name":"commons-e529fd12877672bf1c00.js","size":88589},{"name":"component---src-pages-experience-js-1f9635425bd62f5d5572.js","size":3236}],"filteredAssets":0,"assetsSize":244079,"filteredAuxiliaryAssets":5,"auxiliaryAssetsSize":1638631},"component---src-pages-index-js":{"name":"component---src-pages-index-js","assets":[{"name":"styles.74c3acc855b59ef6f956.css","size":148360},{"name":"cb1608f2-0992558c61e10c50e999.js","size":1707},{"name":"a9a7754c-816c2ce5780ea77fc95e.js","size":2187},{"name":"commons-e529fd12877672bf1c00.js","size":88589},{"name":"6cf1ab06f31558239a7851f0ba16511ad5d09edf-fe5878115318c1cf7033.js","size":15944},{"name":"1f7a1e317deb6f679edf2553d304721106db1456-6c99e90d963f3174ecba.js","size":11533},{"name":"component---src-pages-index-js-f5fceca10335e5fbcaa4.js","size":2897}],"filteredAssets":0,"assetsSize":271217,"filteredAuxiliaryAssets":8,"auxiliaryAssetsSize":3248393},"component---src-pages-projects-js":{"name":"component---src-pages-projects-js","assets":[{"name":"styles.74c3acc855b59ef6f956.css","size":148360},{"name":"cb1608f2-0992558c61e10c50e999.js","size":1707},{"name":"a9a7754c-816c2ce5780ea77fc95e.js","size":2187},{"name":"commons-e529fd12877672bf1c00.js","size":88589},{"name":"component---src-pages-projects-js-033c0079eb5f4368b2aa.js","size":3720}],"filteredAssets":0,"assetsSize":244563,"filteredAuxiliaryAssets":5,"auxiliaryAssetsSize":1640591},"component---src-templates-blog-tag-page-temp-js":{"name":"component---src-templates-blog-tag-page-temp-js","assets":[{"name":"styles.74c3acc855b59ef6f956.css","size":148360},{"name":"cb1608f2-0992558c61e10c50e999.js","size":1707},{"name":"a9a7754c-816c2ce5780ea77fc95e.js","size":2187},{"name":"commons-e529fd12877672bf1c00.js","size":88589},{"name":"6cf1ab06f31558239a7851f0ba16511ad5d09edf-fe5878115318c1cf7033.js","size":15944},{"name":"1f7a1e317deb6f679edf2553d304721106db1456-6c99e90d963f3174ecba.js","size":11533},{"name":"component---src-templates-blog-tag-page-temp-js-7eb8db1cbf47e9719934.js","size":3319}],"filteredAssets":0,"assetsSize":271639,"filteredAuxiliaryAssets":7,"auxiliaryAssetsSize":1754282},"component---src-templates-blog-temp-js":{"name":"component---src-templates-blog-temp-js","assets":[{"name":"styles.74c3acc855b59ef6f956.css","size":148360},{"name":"cb1608f2-0992558c61e10c50e999.js","size":1707},{"name":"a9a7754c-816c2ce5780ea77fc95e.js","size":2187},{"name":"commons-e529fd12877672bf1c00.js","size":88589},{"name":"6cf1ab06f31558239a7851f0ba16511ad5d09edf-fe5878115318c1cf7033.js","size":15944},{"name":"component---src-templates-blog-temp-js-43779808f66a5b6d3e33.js","size":6195}],"filteredAssets":0,"assetsSize":262982,"filteredAuxiliaryAssets":6,"auxiliaryAssetsSize":1714674},"component---src-templates-experience-temp-js":{"name":"component---src-templates-experience-temp-js","assets":[{"name":"styles.74c3acc855b59ef6f956.css","size":148360},{"name":"cb1608f2-0992558c61e10c50e999.js","size":1707},{"name":"a9a7754c-816c2ce5780ea77fc95e.js","size":2187},{"name":"commons-e529fd12877672bf1c00.js","size":88589},{"name":"6cf1ab06f31558239a7851f0ba16511ad5d09edf-fe5878115318c1cf7033.js","size":15944},{"name":"component---src-templates-experience-temp-js-e7afdc8322c6b4f1da06.js","size":7704}],"filteredAssets":0,"assetsSize":264491,"filteredAuxiliaryAssets":6,"auxiliaryAssetsSize":1719305},"component---src-templates-project-temp-js":{"name":"component---src-templates-project-temp-js","assets":[{"name":"styles.74c3acc855b59ef6f956.css","size":148360},{"name":"cb1608f2-0992558c61e10c50e999.js","size":1707},{"name":"a9a7754c-816c2ce5780ea77fc95e.js","size":2187},{"name":"commons-e529fd12877672bf1c00.js","size":88589},{"name":"6cf1ab06f31558239a7851f0ba16511ad5d09edf-fe5878115318c1cf7033.js","size":15944},{"name":"component---src-templates-project-temp-js-1f92cf93796c4b881d42.js","size":8334}],"filteredAssets":0,"assetsSize":265121,"filteredAuxiliaryAssets":6,"auxiliaryAssetsSize":1720740}},"assetsByChunkName":{"polyfill":["webpack-runtime-f513447bffaa63b50010.js","polyfill-5abccd0ea9f5cedded36.js"],"app":["webpack-runtime-f513447bffaa63b50010.js","styles.74c3acc855b59ef6f956.css","framework-c7a97ca6659000a10433.js","app-e723c4ebbc0c587518bd.js"],"component---src-pages-404-js":["styles.74c3acc855b59ef6f956.css","cb1608f2-0992558c61e10c50e999.js","a9a7754c-816c2ce5780ea77fc95e.js","commons-e529fd12877672bf1c00.js","component---src-pages-404-js-058df25e754af4518db9.js"],"component---src-pages-about-js":["styles.74c3acc855b59ef6f956.css","cb1608f2-0992558c61e10c50e999.js","a9a7754c-816c2ce5780ea77fc95e.js","commons-e529fd12877672bf1c00.js","6cf1ab06f31558239a7851f0ba16511ad5d09edf-fe5878115318c1cf7033.js","component---src-pages-about-js-a75361efb4041cdeb4e8.js"],"component---src-pages-blogs-js":["styles.74c3acc855b59ef6f956.css","cb1608f2-0992558c61e10c50e999.js","a9a7754c-816c2ce5780ea77fc95e.js","commons-e529fd12877672bf1c00.js","6cf1ab06f31558239a7851f0ba16511ad5d09edf-fe5878115318c1cf7033.js","1f7a1e317deb6f679edf2553d304721106db1456-6c99e90d963f3174ecba.js","component---src-pages-blogs-js-1d3d449acdeba14cc623.js"],"component---src-pages-experience-js":["styles.74c3acc855b59ef6f956.css","cb1608f2-0992558c61e10c50e999.js","a9a7754c-816c2ce5780ea77fc95e.js","commons-e529fd12877672bf1c00.js","component---src-pages-experience-js-1f9635425bd62f5d5572.js"],"component---src-pages-index-js":["styles.74c3acc855b59ef6f956.css","cb1608f2-0992558c61e10c50e999.js","a9a7754c-816c2ce5780ea77fc95e.js","commons-e529fd12877672bf1c00.js","6cf1ab06f31558239a7851f0ba16511ad5d09edf-fe5878115318c1cf7033.js","1f7a1e317deb6f679edf2553d304721106db1456-6c99e90d963f3174ecba.js","component---src-pages-index-js-f5fceca10335e5fbcaa4.js"],"component---src-pages-projects-js":["styles.74c3acc855b59ef6f956.css","cb1608f2-0992558c61e10c50e999.js","a9a7754c-816c2ce5780ea77fc95e.js","commons-e529fd12877672bf1c00.js","component---src-pages-projects-js-033c0079eb5f4368b2aa.js"],"component---src-templates-blog-tag-page-temp-js":["styles.74c3acc855b59ef6f956.css","cb1608f2-0992558c61e10c50e999.js","a9a7754c-816c2ce5780ea77fc95e.js","commons-e529fd12877672bf1c00.js","6cf1ab06f31558239a7851f0ba16511ad5d09edf-fe5878115318c1cf7033.js","1f7a1e317deb6f679edf2553d304721106db1456-6c99e90d963f3174ecba.js","component---src-templates-blog-tag-page-temp-js-7eb8db1cbf47e9719934.js"],"component---src-templates-blog-temp-js":["styles.74c3acc855b59ef6f956.css","cb1608f2-0992558c61e10c50e999.js","a9a7754c-816c2ce5780ea77fc95e.js","commons-e529fd12877672bf1c00.js","6cf1ab06f31558239a7851f0ba16511ad5d09edf-fe5878115318c1cf7033.js","component---src-templates-blog-temp-js-43779808f66a5b6d3e33.js"],"component---src-templates-experience-temp-js":["styles.74c3acc855b59ef6f956.css","cb1608f2-0992558c61e10c50e999.js","a9a7754c-816c2ce5780ea77fc95e.js","commons-e529fd12877672bf1c00.js","6cf1ab06f31558239a7851f0ba16511ad5d09edf-fe5878115318c1cf7033.js","component---src-templates-experience-temp-js-e7afdc8322c6b4f1da06.js"],"component---src-templates-project-temp-js":["styles.74c3acc855b59ef6f956.css","cb1608f2-0992558c61e10c50e999.js","a9a7754c-816c2ce5780ea77fc95e.js","commons-e529fd12877672bf1c00.js","6cf1ab06f31558239a7851f0ba16511ad5d09edf-fe5878115318c1cf7033.js","component---src-templates-project-temp-js-1f92cf93796c4b881d42.js"]},"childAssetsByChunkName":{}}